sargeparse
