Metadata-Version: 1.2
Name: sargeparse
Version: 0.2.11
Summary: A mildly opinionated argument parsing library based on argparse
Home-page: https://github.com/DiegoPomares/sargeparse
Author: Diego Pomares
Author-email: python@diegopomares.com
License: UNKNOWN
Platform: UNKNOWN
Requires-Python: >=3.4
